url_auth/__init__.py
url_auth/admin.py
url_auth/apps.py
url_auth/models.py
url_auth/settings.py
url_auth/utils.py
url_auth/validators.py
url_auth/views.py
urlauth-0.0.1.dist-info/LICENSE
urlauth-0.0.1.dist-info/METADATA
urlauth-0.0.1.dist-info/WHEEL
urlauth-0.0.1.dist-info/top_level.txt
urlauth-0.0.1.dist-info/RECORD
